mpdlcd/__init__.py
mpdlcd/cli.py
mpdlcd/display_fields.py
mpdlcd/display_pattern.py
mpdlcd/enums.py
mpdlcd/lcdrunner.py
mpdlcd/mpdhooks.py
mpdlcd/mpdwrapper.py
mpdlcd/utils.py
mpdlcd/vendor/__init__.py
mpdlcd/vendor/lcdproc/__init__.py
mpdlcd/vendor/lcdproc/screen.py
mpdlcd/vendor/lcdproc/server.py
mpdlcd/vendor/lcdproc/widgets.py
mpdlcd-0.5.2.data/scripts/mpdlcd
mpdlcd-0.5.2.dist-info/LICENSE
mpdlcd-0.5.2.dist-info/METADATA
mpdlcd-0.5.2.dist-info/WHEEL
mpdlcd-0.5.2.dist-info/top_level.txt
mpdlcd-0.5.2.dist-info/RECORD
