Metadata-Version: 2.1
Name: mpdlcd
Version: 0.5.2
Summary: Display MPD status on a lcdproc server.
Home-page: http://github.com/rbarrois/mpdlcd
Author: Raphaël Barrois
Author-email: raphael.barrois+mpdlcd@polytechnique.org
License: MIT
Download-URL: http://pypi.python.org/pypi/mpdlcd/
Keywords: MPD,lcdproc,lcd
Platform: UNKNOWN
Classifier: Development Status :: 4 - Beta
Classifier: Environment :: No Input/Output (Daemon)
Classifier: Intended Audience :: End Users/Desktop
Classifier: License :: OSI Approved :: MIT License
Classifier: Operating System :: OS Independent
Classifier: Programming Language :: Python :: 3.5
Classifier: Programming Language :: Python :: 3.6
Classifier: Topic :: Multimedia :: Sound/Audio
Requires-Dist: python-mpd2
